isimip_utils/__init__.py
isimip_utils/checksum.py
isimip_utils/config.py
isimip_utils/decorators.py
isimip_utils/exceptions.py
isimip_utils/fetch.py
isimip_utils/netcdf.py
isimip_utils/parser.py
isimip_utils/patterns.py
isimip_utils/utils.py
isimip_utils-1.3.2.dist-info/LICENSE
isimip_utils-1.3.2.dist-info/METADATA
isimip_utils-1.3.2.dist-info/WHEEL
isimip_utils-1.3.2.dist-info/top_level.txt
isimip_utils-1.3.2.dist-info/RECORD
