Metadata-Version: 2.1
Name: isimip-utils
Version: 1.3.2
Summary: This package contains common functionality for different ISIMIP tools.
Author-email: Jochen Klar <jochen.klar@pik-potsdam.de>
Maintainer-email: Jochen Klar <jochen.klar@pik-potsdam.de>
License: MIT License
Project-URL: Repository, https://github.com/ISI-MIP/isimip-utils
Classifier: Operating System :: OS Independent
Classifier: License :: OSI Approved :: MIT License
Classifier: Programming Language :: Python :: 3.8
Classifier: Programming Language :: Python :: 3.9
Classifier: Programming Language :: Python :: 3.10
Classifier: Programming Language :: Python :: 3.11
Requires-Python: >=3.8
License-File: LICENSE
Requires-Dist: colorlog
Requires-Dist: netCDF4
Requires-Dist: python-dotenv
Requires-Dist: requests
Provides-Extra: dev
Requires-Dist: build ; extra == 'dev'
Requires-Dist: pre-commit ; extra == 'dev'
Requires-Dist: ruff ; extra == 'dev'
Requires-Dist: twine ; extra == 'dev'
